yfiles_jupyter_graphs_for_sparql/Yfiles_Sparql_Graphs.py
yfiles_jupyter_graphs_for_sparql/__init__.py
yfiles_jupyter_graphs_for_sparql-1.0.0.dist-info/licenses/LICENSE.md
yfiles_jupyter_graphs_for_sparql-1.0.0.dist-info/METADATA
yfiles_jupyter_graphs_for_sparql-1.0.0.dist-info/WHEEL
yfiles_jupyter_graphs_for_sparql-1.0.0.dist-info/top_level.txt
yfiles_jupyter_graphs_for_sparql-1.0.0.dist-info/RECORD
