Metadata-Version: 2.4
Name: yfiles-jupyter-graphs-for-sparql
Version: 1.0.0
Summary: The open-source adapter for working with RDF databases and SPARQL queries in Jupyter notebooks leveraging the yFiles Graphs for Jupyter plugin.
Author-email: yWorks Support Team <yfileshtml@yworks.com>
License: MIT License
Project-URL: License, https://github.com/yWorks/yfiles-jupyter-graphs-for-sparql/blob/main/LICENSE.md
Project-URL: Bug Tracker, https://github.com/yWorks/yfiles-jupyter-graphs-for-sparql/issues
Project-URL: Documentation, https://github.com/yWorks/yfiles-jupyter-graphs-for-sparql/
Project-URL: Repository, https://github.com/yWorks/yfiles-jupyter-graphs-for-sparql.git
Classifier: Framework :: IPython
Classifier: Intended Audience :: Developers
Classifier: Intended Audience :: Science/Research
Classifier: Programming Language :: Python :: 3
Classifier: Operating System :: OS Independent
Classifier: Framework :: Jupyter
Classifier: Framework :: Jupyter :: JupyterLab
Classifier: Framework :: Jupyter :: JupyterLab :: 3
Classifier: Framework :: Jupyter :: JupyterLab :: Extensions
Classifier: Framework :: Jupyter :: JupyterLab :: Extensions :: Prebuilt
Requires-Python: >=3.8
License-File: LICENSE.md
Requires-Dist: yfiles_jupyter_graphs>=1.9.0
Dynamic: license-file
